{
  "New buff unlocked in DEX": "図鑑に新しいバフを追加",
  "You've reached the limit of savedata items! Are you sure to overwrite?": "セーブ枠が上限です。手動セーブを上書きしてもよろしいですか？",
  "You're going to overwrite the saved data!": "セーブデータを上書きします。",
  "Are you sure you want to delete?": "このセーブを削除してもよろしいですか？",
  "Save": "セーブ",
  "Option": "オプション",
  "Quit": "終了",
  "English": "日本語",
  "Story": "ストーリー",
  "Easy": "イージー",
  "Normal": "ノーマル",
  "Hard": "ハード",
  "Default": "デフォルト",
  "Language": "言語",
  "Display": "表示",
  "Resolution": "解像度",
  "Difficulty": "難易度",
  "New entry unlocked: ": "図鑑に新しいエントリを解放: ",
  "~~Press [SELECT] again to quit the game~~": "~~もう一度 [SELECT] でゲームを終了~~",
  "~~Press [START] again to adjust the settings~~": "~~もう一度 [START] で設定を開く~~",
  "~~Press [Y] again to open the saves~~": "~~もう一度 [Y] でセーブ画面を開く~~",
  "~~Press [A] again to start a new game~~": "~~もう一度 [A] で新しいゲームを開始~~",
  "~~Give those buttons a try?~~": "~~ボタンを押して試してみよう~~",
  "~~Click the red [ENTER] key to start a new game~~": "~~赤い [ENTER] キーで新しいゲームを開始~~",
  "~~Click the white [SPACE] key to open the saves~~": "~~白い [SPACE] キーでセーブ画面を開く~~",
  "~~Click the red [ESC] key to quit the game~~": "~~赤い [ESC] キーでゲームを終了~~",
  "~~Click the yellow key to adjust the settings~~": "~~黄色のキーで設定を開く~~",
  "Enter the savefile name": "セーブ名を入力",
  "Auto Save": "オートセーブ",
  "Are you sure you want to Load?": "このセーブを読み込んでもよろしいですか？",
  "BGM": "BGM",
  "SE": "SE",
  "No Content yet": "まだ何もありません",
  "Fullscreen": "フルスクリーン",
  "Window": "ウィンドウ",
  "<color=#368F65> Unreads</color>": "<color=#368F65> 未読</color>",
  "Please press <color=#ff0000>I Key </color>to check new skill in DEX.": "<color=#ff0000>I キー</color>で図鑑から新スキルを確認してください。",
  "Please press <color=#ff0000>Start Button </color>to check new skill in DEX.": "<color=#ff0000>Start ボタン</color>で図鑑から新スキルを確認してください。",
  "I have empathy": "共感力がある",
  "I think independently": "自分の頭で考える",
  "I am a genius": "私は天才",
  "Canned happiness": "缶入りの幸せ",
  "I am miserable and pitiful": "私は悲惨で可哀想",
  "Someone praised me": "誰かに褒められた",
  "Politically correct": "ポリコレ",
  "Bottled happiness": "瓶入りの幸せ",
  "???": "？？？",
  "The keboard warrior": "キーボード戦士",
  "Bagged happiness": "袋入りの幸せ",
  "Boxed happiness": "箱入りの幸せ",
  "***": "＊＊＊",
  "My time is precious": "私の時間は貴重",
  "I have 100M subs on MePipe": "MeTube登録100万",
  "I didn't ask for your help": "頼んでないけど？",
  "Barreled happiness": "樽入りの幸せ",
  "999 Hours played": "プレイ時間999H",
  "I am knowledgeable": "博識である",
  "I am calm and reasonable": "冷静かつ理性的",
  "I am virtuous and brave": "正直で勇敢",
  "I am professional": "私はプロ",
  "I am unique": "私は人と違う",
  "Happy box": "幸せBOX",
  "I am articulate": "私は弁が立つ",
  "I am extremely lucky": "運が極めて良い",
  "The justified reveal": "正義の開示",
  "Proof your purchasing power through kindness.": "善意で自分の購買力を証明する。",
  "The people on the internet say you have to think independently.": "ネットでは「自分の頭で考えろ」と言われている。",
  "Believe that you are a genius.": "自分は天才だと信じよう。",
  "A 355mL can of happiness.": "355mL缶入りの幸せ。",
  "Effectively gain others' attention.": "他人の注目を効率よく集める。",
  "A few simple sentences can make my day.": "数語の褒め言葉で一日中ハッピー。",
  "Why mention science when we're all about political correctness?": "ポリコレ前提で科学なんて関係ない。",
  "A simple bottle of hapiness.": "素朴な瓶入りの幸せ。",
  "Take a guess what I'm about to say.": "私が何を言うか当ててみて。",
  "Use your typing speed to guard your inner insecurities.": "タイピング速度で内なる不安を守る。",
  "A bag full of happiness.": "幸せを詰めた袋。",
  "A well packaged box of happiness.": "上等に箱詰めされた幸せ。",
  "Everyone knows what the censored word is.": "伏字が何かみんな知っている。",
  "Fast paced life makes people feel alive.": "高速な生活こそが「生きてる」実感。",
  "Use top-notch bragging skill to inflict emotional damage to others.": "最高峰の自慢術で他人に精神ダメージを与える。",
  "Trigger someone so much that they literally take damage.": "相手を発狂させて文字通りHPを削る。",
  "A simply packaged barrel of happiness.": "素朴に樽詰めされた幸せ。",
  "Out of my way, rookie! Just watch and learn.": "道を空けな新人！黙って見て学べ。",
  "Knowledge is the unconquered shield.": "知識は無敵の盾。",
  "Crystal clear cogitation solves every difficulty.": "澄み切った思考があらゆる難題を解く。",
  "Infernal ablaze indignation purges any iniquity.": "燃え盛る怒りが全ての悪を浄化する。",
  "I know you don't understand, I'm talking just because you don't understand.": "君が理解できないのは知っている。理解できないからこそ語るのだ。",
  "I'm not the only one who thinks this way right?": "こう思ってるの私だけじゃないよね？",
  "The ultimate form of a human being: all negative emotions are removed, remaining pure happiness.": "人類の究極形態。負の感情はすべて取り除かれ、純粋な幸福だけが残る。",
  "Speech is the all-conquering spear.": "言葉は無敵の矛。",
  "Lucky people often live a longer life.": "運の良い者はえてして長生きする。",
  "Blow up their virtual facade.": "ネット上の虚構を爆破せよ。",
  "Item description: ": "商品説明： ",
  "What's up!": "なになに！",
  "Who is that guy?\n Why is she standing by Yun Xing": "あの人だれ？\nなんで允星と仲良くしてんの",
  "There must be an \nEXPLANATION!": "ちゃんと\n説明しろー！",
  "The admin power has \nWITHERED!": "管理権限が\n剥奪された！",
  "Why did the mods \nremove those images?!": "なんで管理は\nあの画像消したの！？",
  "Those selfish mods are \nenjoying the images themselves!": "管理ども独り占めで\n画像楽しんでるじゃん！",
  "Overthrow the mods!": "管理を倒せ！",
  "Battle against the mods?\nHah, that's going to \nbe very interesting.": "管理と戦争？\nハハッ、こりゃ\n面白くなってきた。",
  "Who cares!": "知るかよ！",
  "Are you one of \nthe mods' lackeys?": "あんた管理の\n犬かよ？",
  "There's definitely something\n wrong with this person.": "この人マジで\nやばいやつでしょ。",
  "What a loser lol": "雑魚すぎワロタ",
  "Yeah, what an \nabsolute loser!": "そう、ガチ\n雑魚じゃん！",
  "Overthrow the tyrant mod!": "暴君管理を倒せ！",
  "Watch out for the moments. Rebounce the bullets with weak attack.": "タイミングを見て、弱攻撃で弾を打ち返せ。",
  "Jump and step on the grid to <color=#ff0000>sweep all mines</color>.": "ジャンプして床を踏み、<color=#ff0000>地雷を全て除去</color>するのだ。",
  "Why not google for the rule of <color=#ff0000>Chinese Cheese</color>?": "<color=#ff0000>中国将棋（シャンチー）</color>のルールはググってみるのだ。",
  "<color=#ff0000>Stun</color> Fuxi through bumping herself on <color=#ff0000>keycaps</color>.": "ボスを<color=#ff0000>キーキャップ</color>に激突させて<color=#ff0000>スタン</color>させるのだ。",
  "You just unlocked a buff.": "新しいバフを解放した。",
  "You can press<color=#ff0000> Key 1 to 4</color> to use it.": "<color=#ff0000>キーボード1〜4</color>を押して使えるのだ。",
  "You can press <color=#ff0000>D-Pad button </color>to use it.": "<color=#ff0000>十字キー</color>を押して使えるのだ。",
  "Click <color=#ff0000>Green button at top right corner</color> to use cheater.": "<color=#ff0000>右上の緑ボタン</color>でチート機能が使えるのだ。",
  "You can <color=#ff0000>choose difficulty</color> in <color=#ff0000>\"Option\"</color>": "<color=#ff0000>オプション</color>で<color=#ff0000>難易度</color>を選べるのだ。",
  "AutoSave ": "オートセーブ ",
  "Unnamed Save": "無名のセーブ",
  "战斗前": "戦闘前",
  "战斗中": "戦闘中",
  "战斗后": "戦闘後"
}